{
  "dateCreation": "09/06/20 15:36",
  "dateSoumission": "09/06/20 15:59",
  "numeroCfe": "U13078231195",
  "codeFormCerfa": "P0PLME",
  "liasseWeb": {
    "Entreprise/Etablissement/ACE/E71": "GUIDE INTERPRETE",
    "Entreprise/Etablissement/ACE/E70": "GUIDE INTERPRETE",
    "PersonnePhysique/GCS/SNS/A24/A24.1": "N",
    "Service/ADF/C39/C39.1[1]": "0821132227",
    "Entreprise/OVU/U42": "N",
    "PersonnePhysique/GCS/MSS/A31/A31.2": "M",
    "Entreprise/Etablissement/ICE/E02/E02.13": "NICE",
    "Entreprise/Etablissement/CAE/E73/E73.1": "P",
    "Entreprise/Etablissement/ICE/E02/E02.12": "98",
    "Entreprise/CPU/U21": "GUIDE INTERPRETE",
    "Service/ADF/C37/C37.3": "06088",
    "Service/SIF/C40/C40.1": "TestPréInscritEmail TestPréInscritEmai",
    "Service/SIF/C42": "2020-06-09",
    "Service/ADF/C39/C39.1[0]": "0821132227",
    "Service/SIF/C45": "O",
    "Service/IDF/C07": "O",
    "Entreprise/Etablissement/CAE/E75/E75.2": "Profession libérale",
    "Service/IDF/C05": "X",
    "Service/IDF/C03": "0",
    "Entreprise/Etablissement/CAE/E75/E75.1": "99",
    "Service/IDF/C02": "U1307W000208",
    "Service/IDF/C01": "2020-06-09",
    "Entreprise/SIU/U11/U11.3": "06088",
    "PersonnePhysique/ICP/P03/P03.4": "NICE",
    "Entreprise/SIU/U11/U11.8": "06000",
    "PersonnePhysique/ICP/P03/P03.1": "2004-06-09",
    "Entreprise/Etablissement/ICE/E02/E02.8": "06000",
    "PersonnePhysique/ICP/P03/P03.2": "06088",
    "Service/ADF/C39/C39.3": "testpreinscritemail_1@yopmail.com",
    "Entreprise/Etablissement/ICE/E02/E02.3": "06088",
    "Entreprise/Etablissement/SAE/E84": "0",
    "PersonnePhysique/GCS/ISS/A10/A10.1": "0000000000000",
    "Entreprise/SIU/U11/U11.13": "NICE",
    "PersonnePhysique/GCS/ISS/A10/A10.2": "00",
    "Entreprise/Etablissement/SAE/E86": "N",
    "Entreprise/SIU/U11/U11.12": "98",
    "PersonnePhysique/ICP/P07": "O",
    "PersonnePhysique/NAP/P21": "FRANCAISE",
    "PersonnePhysique/ICP/P04/P04.13": "NICE",
    "PersonnePhysique/ICP/P04/P04.12": "98",
    "PersonnePhysique/ICP/P01/P01.2": "TestPréInscritEmai",
    "Entreprise/Etablissement/ORE/E21/E21.1": "1",
    "PersonnePhysique/ICP/P01/P01.1": "1",
    "PersonnePhysique/GCS/MSS/A31/A31.1": "O",
    "Entreprise/Etablissement/ICE/E04": "2",
    "PersonnePhysique/ICP/P01/P01.3": "TestPréInscritEmail",
    "Service/EDF/C10/C10.3": "2",
    "Service/ADF/C37/C37.8": "06000",
    "Entreprise/Etablissement/ICE/E09": "ppop",
    "PersonnePhysique/GCS/SNS/A23": "O",
    "Service/DMF/C20": "U1307",
    "Service/EDF/C10/C10.2": "2020-06-09",
    "Service/ADF/C36": "TestPréInscritEmai TestPréInscritEmail",
    "Service/EDF/C10/C10.1": "01P",
    "PersonnePhysique/ICP/P04/P04.8": "06000",
    "Service/ADF/C37/C37.13": "NICE",
    "Entreprise/Etablissement/ICE/E01": "1",
    "Service/ADF/C37/C37.12": "98",
    "PersonnePhysique/ICP/P04/P04.3": "06088"
  }
}
